kryptonic/__init__.py
kryptonic/__main__.py
kryptonic/keys.py
kryptonic/krtest.py
kryptonic/options.py
kryptonic-0.9.0.dist-info/METADATA
kryptonic-0.9.0.dist-info/WHEEL
kryptonic-0.9.0.dist-info/top_level.txt
kryptonic-0.9.0.dist-info/RECORD
